create_testing_pypi_maheshmakwana787/__init__.py
create_testing_pypi_maheshmakwana787/audio.py
create_testing_pypi_maheshmakwana787/streaming.py
vidstream/__init__.py
vidstream/audio.py
vidstream/streaming.py
create_testing_pypi_maheshmakwana787-0.0.2.dist-info/LICENSE
create_testing_pypi_maheshmakwana787-0.0.2.dist-info/METADATA
create_testing_pypi_maheshmakwana787-0.0.2.dist-info/WHEEL
create_testing_pypi_maheshmakwana787-0.0.2.dist-info/top_level.txt
create_testing_pypi_maheshmakwana787-0.0.2.dist-info/RECORD
